fastdataframe/__init__.py
fastdataframe/py.typed
fastdataframe/core/__init__.py
fastdataframe/core/annotation.py
fastdataframe/core/json_schema.py
fastdataframe/core/model.py
fastdataframe/core/types.py
fastdataframe/core/types_helper.py
fastdataframe/core/validation.py
fastdataframe/core/pydantic/__init__.py
fastdataframe/core/pydantic/field_info.py
fastdataframe/iceberg/__init__.py
fastdataframe/iceberg/json_schema.py
fastdataframe/iceberg/model.py
fastdataframe/polars/__init__.py
fastdataframe/polars/_cast_functions.py
fastdataframe/polars/_types.py
fastdataframe/polars/datetime_format.py
fastdataframe/polars/model.py
fastdataframe-0.1.0.dist-info/METADATA
fastdataframe-0.1.0.dist-info/WHEEL
fastdataframe-0.1.0.dist-info/licenses/LICENSE
fastdataframe-0.1.0.dist-info/RECORD
